{
  "code": 0,
  "data": {
    "cid": "6426",
    "type": 0,
    "tab": "events",
    "orderType": 0,
    "orderWeight": 1,
    "displayType": "rich_text",
    "focus": 0,
    "startAt": 1784156400,
    "title": "向渊行\\n版本日历",
    "header": "「向渊行」版本日历",
    "jumpButton": null,
    "data": {
      "html": "<img src=\"https://web.hycdn.cn/upload/image/20260722/14dada3494474407ae343262e7370d40.png\" data-width=\"1920\" data-height=\"2901\"><p></p>",
      "linkType": 1
    },
    "needRedDot": false,
    "needPopup": false,
    "version": 1784714884
  },
  "msg": ""
}